yta_project_editor/__init__.py
yta_project_editor/settings.py
yta_project_editor/timeline_track/__init__.py
yta_project_editor/timeline_track/audio.py
yta_project_editor/timeline_track/elements/__init__.py
yta_project_editor/timeline_track/elements/audio.py
yta_project_editor/timeline_track/elements/subtitles.py
yta_project_editor/timeline_track/elements/video.py
yta_project_editor/timeline_track/video.py
yta_project_editor/validator.py
yta_project_editor-0.0.5.dist-info/licenses/LICENSE
yta_project_editor-0.0.5.dist-info/METADATA
yta_project_editor-0.0.5.dist-info/WHEEL
yta_project_editor-0.0.5.dist-info/RECORD
