Metadata-Version: 2.4
Name: yta-project-editor
Version: 0.0.5
Summary: Youtube Autonomous Project Editor Module
License-File: LICENSE
Author: danialcala94
Author-email: danielalcalavalera@gmail.com
Requires-Python: ==3.9
Classifier: Programming Language :: Python :: 3
Classifier: Programming Language :: Python :: 3.9
Requires-Dist: yta_constants (>=0.0.1,<1.0.0)
Requires-Dist: yta_validation (>=0.0.1,<1.0.0)
Requires-Dist: yta_video_base (>=0.0.1,<1.0.0)
Requires-Dist: yta_video_editor (>=0.0.1,<1.0.0)
Requires-Dist: yta_video_frame_time (>=0.0.1,<1.0.0)
Requires-Dist: yta_video_moviepy (>=0.0.1,<1.0.0)
Requires-Dist: yta_video_utils (>=0.0.1,<1.0.0)
